lab304/__init__.py
lab304/dl.py
lab304-0.0.2.dist-info/METADATA
lab304-0.0.2.dist-info/WHEEL
lab304-0.0.2.dist-info/top_level.txt
lab304-0.0.2.dist-info/RECORD
